{
  "platform": "yahoo_rushbuy",
  "keyword": "yahoo_rushbuy",
  "total_products": 26,
  "products": [
    {
      "title": "【New Balance】熱銷補貨款1906復古鞋_IU著用款",
      "price": 3311,
      "image_url": "https://img.yec.tw/zp/MerchandiseImages/E068157F0B-Gd-11451754.jpg",
      "url": "https://tw.buy.yahoo.com/gdsale/gdsale.asp?gdid=11451754",
      "platform": "yahoo_rushbuy"
    },
    {
      "title": "【悠活原力】原力維生素D 800IU錠(120錠/瓶) x5瓶",
      "price": 869,
      "image_url": "https://img.yec.tw/zp/MerchandiseImages/1f94ae76c2-Gd-11503267.jpg",
      "url": "https://tw.buy.yahoo.com/gdsale/gdsale.asp?gdid=11503267",
      "platform": "yahoo_rushbuy"
    },
    {
      "title": "ONPRO MA-SPN5 Plus 真無線藍牙5.4磁吸小夜燈喇叭",
      "price": 499,
      "image_url": "https://img.yec.tw/zp/MerchandiseImages/78B1D5B61F-SP-20503973.jpg",
      "url": "https://tw.buy.yahoo.com/gdsale/gdsale.asp?gdid=11687381",
      "platform": "yahoo_rushbuy"
    },
    {
      "title": "券後價$1599【New Balance】725系列復古鞋_中性_多款任選(ML725CK/ML725P/ML725CG/ML725CH)(Y購/網路獨家)",
      "price": 1599,
      "image_url": "https://img.yec.tw/zp/MerchandiseImages/D066595833-Gd-11680988.jpg",
      "url": "https://tw.buy.yahoo.com/gdsale/gdsale.asp?gdid=11680988",
      "platform": "yahoo_rushbuy"
    },
    {
      "title": "韓國熊津 任選兩盒-紅蔘飲禮盒 (24入/盒)",
      "price": 1656,
      "image_url": "https://img.yec.tw/zp/MerchandiseImages/9F3B21A87B-SP-18549620.jpg",
      "url": "https://tw.buy.yahoo.com/gdsale/gdsale.asp?gdid=11409875",
      "platform": "yahoo_rushbuy"
    },
    {
      "title": "【MYCELL】65W GaN 5in1 磁吸式無線充電器",
      "price": 1437,
      "image_url": "https://img.yec.tw/zp/MerchandiseImages/4D5605F8D5-SP-19927813.jpg",
      "url": "https://tw.buy.yahoo.com/gdsale/gdsale.asp?gdid=11604897",
      "platform": "yahoo_rushbuy"
    },
    {
      "title": "李施德霖漱口水750ml+250ml-箱購(6入)任選",
      "price": 939,
      "image_url": "https://img.yec.tw/zp/MerchandiseImages/374efecdd0-Gd-11015693.jpg",
      "url": "https://tw.buy.yahoo.com/gdsale/gdsale.asp?gdid=11036119",
      "platform": "yahoo_rushbuy"
    },
    {
      "title": "Mardi Mercredi 經典小雛菊印花純棉保暖大學TEE 多款任選",
      "price": 1699,
      "image_url": "https://img.yec.tw/zp/MerchandiseImages/7c2fc3ff09-Gd-11864563.jpg",
      "url": "https://tw.buy.yahoo.com/gdsale/gdsale.asp?gdid=11864563",
      "platform": "yahoo_rushbuy"
    },
    {
      "title": "【Soundmaker】ANC-01 Plus 主動降噪真無線藍牙耳機",
      "price": 899,
      "image_url": "https://img.yec.tw/zp/MerchandiseImages/BCD5B7EC10-SP-10410396.jpg",
      "url": "https://tw.buy.yahoo.com/gdsale/gdsale.asp?gdid=9698116",
      "platform": "yahoo_rushbuy"
    },
    {
      "title": "sebamed施巴 油性洗髮乳1000ml 2入組",
      "price": 1439,
      "image_url": "https://img.yec.tw/zp/MerchandiseImages/D5CB6B48A3-Product-17961717.jpg",
      "url": "https://tw.buy.yahoo.com/gdsale/gdsale.asp?gdid=6670574",
      "platform": "yahoo_rushbuy"
    },
    {
      "title": "奇哥 Joie tourist 自動秒收推車",
      "price": 5700,
      "image_url": "https://img.yec.tw/zp/MerchandiseImages/ee510d3b98-Gd-9561305.jpg",
      "url": "https://tw.buy.yahoo.com/gdsale/gdsale.asp?gdid=9561305",
      "platform": "yahoo_rushbuy"
    },
    {
      "title": "L'OCCITANE 歐舒丹 經典護手霜150ml任選",
      "price": 599,
      "image_url": "https://img.yec.tw/zp/MerchandiseImages/5CFEC1CE21-Gd-11478595.jpg",
      "url": "https://tw.buy.yahoo.com/gdsale/gdsale.asp?gdid=11478595",
      "platform": "yahoo_rushbuy"
    },
    {
      "title": "SAMPO聲寶 台灣製 15公斤經典系列定頻直立式洗衣機[箱損新品] 含基本安裝+舊機回收",
      "price": 12361,
      "image_url": "https://img.yec.tw/zp/MerchandiseImages/740B3E16F5-SP-21576122.jpg",
      "url": "https://tw.buy.yahoo.com/gdsale/gdsale.asp?gdid=11901893",
      "platform": "yahoo_rushbuy"
    },
    {
      "title": "芙婷寶 Femarelle 膠囊 56粒/盒",
      "price": 1688,
      "image_url": "https://img.yec.tw/zp/MerchandiseImages/d300a41ea8-Gd-9695779.jpg",
      "url": "https://tw.buy.yahoo.com/gdsale/gdsale.asp?gdid=9695779",
      "platform": "yahoo_rushbuy"
    },
    {
      "title": "微軟 Microsoft M365 Personal 個人版一年盒裝",
      "price": 2150,
      "image_url": "https://img.yec.tw/zp/MerchandiseImages/7A0D6A3BB1-SP-21242608.jpg",
      "url": "https://tw.buy.yahoo.com/gdsale/gdsale.asp?gdid=11836380",
      "platform": "yahoo_rushbuy"
    },
    {
      "title": "韓國MEDITHERAPY 光感修護精華150ml 2入組",
      "price": 780,
      "image_url": "https://img.yec.tw/zp/MerchandiseImages/A1B1EBCFF0-Gd-11877358.jpg",
      "url": "https://tw.buy.yahoo.com/gdsale/gdsale.asp?gdid=11877358",
      "platform": "yahoo_rushbuy"
    },
    {
      "title": "【1/17 時時樂限定】Mdovia V3 Pro Coffee 奶泡專家 義式研磨精萃 全自動義式咖啡機",
      "price": 5980,
      "image_url": "https://img.yec.tw/zp/MerchandiseImages/c39615c663-Gd-11454454.jpg",
      "url": "https://tw.buy.yahoo.com/gdsale/gdsale.asp?gdid=11454454",
      "platform": "yahoo_rushbuy"
    },
    {
      "title": "[任3件1290]曼黛瑪璉&瑪登瑪朵 必收好評款快閃回歸",
      "price": 1290,
      "image_url": "https://img.yec.tw/zp/MerchandiseImages/00B653F5A7-Gd-11926186.jpg",
      "url": "https://tw.buy.yahoo.com/gdsale/gdsale.asp?gdid=11926186",
      "platform": "yahoo_rushbuy"
    },
    {
      "title": "台鹽 海洋鹼性離子水 任選2箱",
      "price": 797,
      "image_url": "https://img.yec.tw/zp/MipImages/C2491A974C-MIP-503243.jpeg",
      "url": "https://tw.buy.yahoo.com/activity/onsale/combo?actid=503243",
      "platform": "yahoo_rushbuy"
    },
    {
      "title": "(下單再折) ASUS 華碩 A23 Hatsune Miku Edition 初音未來限定版電競機殼 A23-MIKU",
      "price": 2190,
      "image_url": "https://img.yec.tw/zp/MerchandiseImages/729532F4E1-SP-21291320.jpg",
      "url": "https://tw.buy.yahoo.com/gdsale/gdsale.asp?gdid=11846217",
      "platform": "yahoo_rushbuy"
    },
    {
      "title": "【Aibo】韓版針織雲朵絨鋪棉保暖水洗被(雙人6x7/多款任選/韓國被/冬被/保暖被)",
      "price": 888,
      "image_url": "https://img.yec.tw/zp/MerchandiseImages/8919670046-Gd-11324608.jpg",
      "url": "https://tw.buy.yahoo.com/gdsale/gdsale.asp?gdid=11324608",
      "platform": "yahoo_rushbuy"
    },
    {
      "title": "佳佳幸福饗宴年菜 六菜組合-預購【1/29陸續出貨】【愛買】",
      "price": 999,
      "image_url": "https://img.yec.tw/cl/api/res/1.2/ckNWI_NYiYKKPJGXsRVJNQ--/YXBwaWQ9eXR3bWFsbDtoPTYwMDtxPTEwMDt3PTYwMA--/https://img.yec.tw/fy/f93e/item/p0830264006090-item-6ebcxf4x0500x0500-m.jpg",
      "url": "https://tw.buy.yahoo.com/gdsale/gdsale.asp?gdid=p0830264006090",
      "platform": "yahoo_rushbuy"
    },
    {
      "title": "毛圈款．動物家族純棉浴巾(4條浴巾組／加贈大方巾) 【台灣興隆毛巾專賣】純棉／熱賣推薦",
      "price": 1250,
      "image_url": "https://img.yec.tw/cl/api/res/1.2/s3CiVYplsoWL.tjs2alF9g--/YXBwaWQ9eXR3bWFsbDtoPTYwMDtxPTEwMDt3PTYwMA--/https://img.yec.tw/fy/c3f7/item/p0290263424035-item-e905xf4x1000x1000-m.jpg",
      "url": "https://tw.buy.yahoo.com/gdsale/gdsale.asp?gdid=p0290263424035",
      "platform": "yahoo_rushbuy"
    },
    {
      "title": "(券後價$1699)【New Balance】327/574/996系列復古鞋_女性_多款任選",
      "price": 1699,
      "image_url": "https://img.yec.tw/zp/MerchandiseImages/BD8620B4CD-Gd-11489859.jpg",
      "url": "https://tw.buy.yahoo.com/gdsale/gdsale.asp?gdid=11489859",
      "platform": "yahoo_rushbuy"
    },
    {
      "title": "【喜憨兒*愛心年菜募集】2026春節送暖到偏鄉 (您不會收到商品)(公益)",
      "price": 399,
      "image_url": "https://img.yec.tw/cl/api/res/1.2/hwEOhFUs1i9qvMPA1vuSnw--/YXBwaWQ9eXR3bWFsbDtoPTYwMDtxPTEwMDt3PTYwMA--/https://img.yec.tw/fy/28b8/item/p0084265288389-item-5f33xf4x1000x1000-m.jpg",
      "url": "https://tw.buy.yahoo.com/gdsale/gdsale.asp?gdid=p0084265288389",
      "platform": "yahoo_rushbuy"
    },
    {
      "title": "[平均單片$117] 4坪/韓國製免膠無痕拼裝LVT塑膠地板 塑化劑 甲醛檢測合格",
      "price": 6999,
      "image_url": "https://img.yec.tw/cl/api/res/1.2/JPUonHBQqrg_EvYwLP851Q--/YXBwaWQ9eXR3bWFsbDtoPTYwMDtxPTEwMDt3PTYwMA--/https://img.yec.tw/fy/6584/item/p0065265364345-item-7a8cxf4x1000x1000-m.jpg",
      "url": "https://tw.buy.yahoo.com/gdsale/gdsale.asp?gdid=p0065265364345",
      "platform": "yahoo_rushbuy"
    }
  ],
  "crawl_time": "2026-01-17 12:25:51"
}