{
  "platform": "yahoo_rushbuy",
  "keyword": "yahoo_rushbuy",
  "total_products": 27,
  "products": [
    {
      "title": "【寶拉珍選】水楊酸身體乳兩入組(2%水楊酸身體乳 210ml x2)+水楊酸身體乳60ml+洗面乳30ml",
      "price": 1500,
      "image_url": "https://img.yec.tw/zp/MerchandiseImages/9596F623EB-Gd-12032658.jpg",
      "url": "https://tw.buy.yahoo.com/gdsale/gdsale.asp?gdid=12032658",
      "platform": "yahoo_rushbuy"
    },
    {
      "title": "【舒潔】雲絨舒適抽取衛生紙-迪士尼季節限定款 90抽x64包/箱",
      "price": 699,
      "image_url": "https://img.yec.tw/zp/MerchandiseImages/C8D1DA2239-Gd-12011567.jpg",
      "url": "https://tw.buy.yahoo.com/gdsale/gdsale.asp?gdid=12011567",
      "platform": "yahoo_rushbuy"
    },
    {
      "title": "【Meiji 明治】膠原蛋白粉璀璨金28日份袋裝(196gx3袋)",
      "price": 2799,
      "image_url": "https://img.yec.tw/zp/MerchandiseImages/2A76976E5A-Gd-10259619.jpg",
      "url": "https://tw.buy.yahoo.com/gdsale/gdsale.asp?gdid=10259619",
      "platform": "yahoo_rushbuy"
    },
    {
      "title": "Cle De Peau 肌膚之鑰 恆霧光潤粉凝露 9ml 兩種色號任選 國際航空版",
      "price": 790,
      "image_url": "https://img.yec.tw/zp/MerchandiseImages/086AB5D9E6-SP-22059739.jpg",
      "url": "https://tw.buy.yahoo.com/gdsale/gdsale.asp?gdid=11982739",
      "platform": "yahoo_rushbuy"
    },
    {
      "title": "PERKINS伯金仕 獨家品牌精選0.40克拉18K金天然鑽石項鍊",
      "price": 19988,
      "image_url": "https://img.yec.tw/zp/MerchandiseImages/0f81777478-Gd-12023773.jpg",
      "url": "https://tw.buy.yahoo.com/gdsale/gdsale.asp?gdid=12023773",
      "platform": "yahoo_rushbuy"
    },
    {
      "title": "Acer 宏碁 C24-195ES 24型AIO桌上型電腦(CU5-125U/8GB/512GB/Win11)",
      "price": 19999,
      "image_url": "https://img.yec.tw/zp/MerchandiseImages/F087CBAEF1-Gd-11141100.jpg",
      "url": "https://tw.buy.yahoo.com/gdsale/gdsale.asp?gdid=11141100",
      "platform": "yahoo_rushbuy"
    },
    {
      "title": "【WEDAR薇達】 金盞花葉黃素x6盒 (網路限定版)",
      "price": 889,
      "image_url": "https://img.yec.tw/zp/MerchandiseImages/81FB4D6357-Gd-10894366.jpg",
      "url": "https://tw.buy.yahoo.com/gdsale/gdsale.asp?gdid=10894366",
      "platform": "yahoo_rushbuy"
    },
    {
      "title": "爆款$999【adidas 愛迪達】男/女 精選運動鞋休閒鞋 任選均一價",
      "price": 999,
      "image_url": "https://img.yec.tw/zp/MerchandiseImages/BEC71B655E-Gd-11911017.jpg",
      "url": "https://tw.buy.yahoo.com/gdsale/gdsale.asp?gdid=11911017",
      "platform": "yahoo_rushbuy"
    },
    {
      "title": "Dirt Devil Detruire PRO 【大白】 高扭力研磨 3L智能偵測廚餘機【符合補助機款】",
      "price": 3680,
      "image_url": "https://img.yec.tw/zp/MerchandiseImages/1fa0c9607b-Gd-10410795.jpg",
      "url": "https://tw.buy.yahoo.com/gdsale/gdsale.asp?gdid=10410795",
      "platform": "yahoo_rushbuy"
    },
    {
      "title": "United Athle 5001-01 5.6OZ 舒適 短TEE",
      "price": 170,
      "image_url": "https://img.yec.tw/zp/MerchandiseImages/4064B3EB12-Gd-11805102.jpg",
      "url": "https://tw.buy.yahoo.com/gdsale/gdsale.asp?gdid=11805102",
      "platform": "yahoo_rushbuy"
    },
    {
      "title": "1028 超能曬維他命C水感防曬乳SPF50+ PA++++2入",
      "price": 225,
      "image_url": "https://img.yec.tw/zp/MerchandiseImages/0A1F2D41FA-Gd-11536882.jpg",
      "url": "https://tw.buy.yahoo.com/gdsale/gdsale.asp?gdid=11536882",
      "platform": "yahoo_rushbuy"
    },
    {
      "title": "【小倉Ogula】現代簡約學習辦公護眼led無極調光插電馬卡龍木頭檯燈（護眼燈/床頭燈/閱讀燈/學習燈）",
      "price": 779,
      "image_url": "https://img.yec.tw/zp/MerchandiseImages/F163493A03-Gd-10908305.jpg",
      "url": "https://tw.buy.yahoo.com/gdsale/gdsale.asp?gdid=10908305",
      "platform": "yahoo_rushbuy"
    },
    {
      "title": "【Gigastone】100W GaN 氮化鎵三孔充電器 + C to C 100W快充傳輸線 快充組(PD-100B+CC-7800B)",
      "price": 899,
      "image_url": "https://img.yec.tw/zp/MerchandiseImages/4C38705A03-SP-14625568.jpg",
      "url": "https://tw.buy.yahoo.com/gdsale/gdsale.asp?gdid=10696417",
      "platform": "yahoo_rushbuy"
    },
    {
      "title": "Olitalia奧利塔純橄欖油禮盒組(1000mlx2瓶)(時時樂)",
      "price": 899,
      "image_url": "https://img.yec.tw/zp/MerchandiseImages/B480C7EAEB-SP-12336174.jpg",
      "url": "https://tw.buy.yahoo.com/gdsale/gdsale.asp?gdid=10288723&sw=dddd74a70186f43a",
      "platform": "yahoo_rushbuy"
    },
    {
      "title": "山打努SANDARU～復古甜美瑪莉珍鞋 厚底鞋 娃娃鞋 低跟鞋 (多款任選)(時時樂限定)",
      "price": 880,
      "image_url": "https://img.yec.tw/zp/MerchandiseImages/049ce84bec-Gd-11697459.jpg",
      "url": "https://tw.buy.yahoo.com/gdsale/gdsale.asp?gdid=11697459",
      "platform": "yahoo_rushbuy"
    },
    {
      "title": "ANDYMAY2 大櫻經典款雙開門折疊收納櫃 收納箱_規格任選 (290L-70寬五層/370L-80寬四層) AM-R601【收納箱 置物櫃 收納架】",
      "price": 950,
      "image_url": "https://img.yec.tw/zp/MerchandiseImages/7746D1D77D-SP-19327023.jpg",
      "url": "https://tw.buy.yahoo.com/gdsale/gdsale.asp?gdid=11525545",
      "platform": "yahoo_rushbuy"
    },
    {
      "title": "Anker A1637 10000mAh 30W 自帶線自帶插頭快充行動電源(國際通用插頭)",
      "price": 999,
      "image_url": "https://img.yec.tw/zp/MerchandiseImages/fc42a240ee-Gd-11634777.jpg",
      "url": "https://tw.buy.yahoo.com/gdsale/gdsale.asp?gdid=11634777",
      "platform": "yahoo_rushbuy"
    },
    {
      "title": "【悠活原力】YOHO敏立清乳鐵蛋白益生菌-乳酸(30入/盒)x2盒",
      "price": 1376,
      "image_url": "https://img.yec.tw/zp/MerchandiseImages/222F6A6CE4-Gd-12000806.jpg",
      "url": "https://tw.buy.yahoo.com/gdsale/gdsale.asp?gdid=12000806",
      "platform": "yahoo_rushbuy"
    },
    {
      "title": "【世紀白金】Pt950 鉑金 白金 豆形 墜子 鎖骨項鍊 女款簡約百搭 禮物",
      "price": 16388,
      "image_url": "https://img.yec.tw/zp/MerchandiseImages/4AC6EB29BC-SP-22576475.jpg",
      "url": "https://tw.buy.yahoo.com/gdsale/gdsale.asp?gdid=12079554",
      "platform": "yahoo_rushbuy"
    },
    {
      "title": "SUNTORY 三得利 vitoas蜜得絲多效極妍鎖濕菁華 (1ml x 120包)",
      "price": 1800,
      "image_url": "https://img.yec.tw/zp/MerchandiseImages/5ce0ba6f87-Gd-8701747.jpg",
      "url": "https://tw.buy.yahoo.com/gdsale/gdsale.asp?gdid=8701747",
      "platform": "yahoo_rushbuy"
    },
    {
      "title": "舒主金加蓋純水濕紙巾80抽x36包 台灣製 濕巾",
      "price": 711,
      "image_url": "https://img.yec.tw/zp/MerchandiseImages/F3013B0AE5-SP-15073658.jpg",
      "url": "https://tw.buy.yahoo.com/gdsale/gdsale.asp?gdid=10776453",
      "platform": "yahoo_rushbuy"
    },
    {
      "title": "【NIKE】NIKE KAWA SLIDE (GS/PS) 運動拖鞋 男女/大童 A-819352003 B-CZ7836001 C-CZ7836100",
      "price": 399,
      "image_url": "https://img.yec.tw/zp/MerchandiseImages/ADA45ADD0C-SP-20577385.jpg",
      "url": "https://tw.buy.yahoo.com/gdsale/gdsale.asp?gdid=11698883",
      "platform": "yahoo_rushbuy"
    },
    {
      "title": "日本DALE達樂可調頻5段式伸縮沖牙器DL-5005",
      "price": 699,
      "image_url": "https://img.yec.tw/cl/api/res/1.2/WHmagHdzIWHffweo8HW2yQ--/YXBwaWQ9eXR3bWFsbDtoPTYwMDtxPTEwMDt3PTYwMA--/https://img.yec.tw/fy/54be/item/p0490264028910-item-6fbfxf4x0800x0800-m.jpg",
      "url": "https://tw.buy.yahoo.com/gdsale/gdsale.asp?gdid=p0490264028910",
      "platform": "yahoo_rushbuy"
    },
    {
      "title": "【促銷組】善存 葉黃素 20mg (60粒/2盒)｜游離型軟膠囊【杏一】",
      "price": 1249,
      "image_url": "https://img.yec.tw/cl/api/res/1.2/eDnpW8w1MQEkfWMEVPwWUw--/YXBwaWQ9eXR3bWFsbDtoPTYwMDtxPTEwMDt3PTYwMA--/https://img.yec.tw/fy/8b03/item/p0216264909432-item-3f41xf4x1000x1000-m.jpg",
      "url": "https://tw.buy.yahoo.com/gdsale/gdsale.asp?gdid=p0216264909432",
      "platform": "yahoo_rushbuy"
    },
    {
      "title": "台客嚴選_亞達韓風紓壓和室椅 和室椅 收納椅 MIT",
      "price": 1692,
      "image_url": "https://img.yec.tw/cl/api/res/1.2/jyjMiQy4g_IgdCU8l1z3Gw--/YXBwaWQ9eXR3bWFsbDtoPTYwMDtxPTEwMDt3PTYwMA--/https://img.yec.tw/fy/83c7/item/p0996263007915-item-0c02xf4x1000x1000-m.jpg",
      "url": "https://tw.buy.yahoo.com/gdsale/gdsale.asp?gdid=p0996263007915",
      "platform": "yahoo_rushbuy"
    },
    {
      "title": "【班尼斯乳膠枕】正宗馬來西亞麵包型天然乳膠枕頭(升級大和抗菌棉織布套)，超取限兩顆！",
      "price": 980,
      "image_url": "https://img.yec.tw/cl/api/res/1.2/Txrj4p6z6eYMQ7zsVx68zw--/YXBwaWQ9eXR3bWFsbDtoPTYwMDtxPTEwMDt3PTYwMA--/https://img.yec.tw/fy/2fea/item/p0454178866989-item-ab9dxf4x1000x1000-m.jpg",
      "url": "https://tw.buy.yahoo.com/gdsale/gdsale.asp?gdid=p0454178866989",
      "platform": "yahoo_rushbuy"
    },
    {
      "title": "領券折100 | 短靴．街頭皮革拼接切爾西防水雨靴",
      "price": 699,
      "image_url": "https://img.yec.tw/cl/api/res/1.2/jJClM0jrTBDDo.5ZH2Y4sQ--/YXBwaWQ9eXR3bWFsbDtoPTYwMDtxPTEwMDt3PTYwMA--/https://img.yec.tw/fy/900f/item/p0475264932325-item-da76xf4x0600x0600-m.jpg",
      "url": "https://tw.buy.yahoo.com/gdsale/gdsale.asp?gdid=p0475264932325",
      "platform": "yahoo_rushbuy"
    }
  ],
  "crawl_time": "2026-05-18 19:27:18"
}