{
  "platform": "yahoo_rushbuy",
  "keyword": "yahoo_rushbuy",
  "total_products": 23,
  "products": [
    {
      "title": "【葡萄王】限時加碼300超贈點-益菌王膠囊60粒x4瓶",
      "price": 1500,
      "image_url": "https://img.yec.tw/zp/MerchandiseImages/ea83bbe68e-Gd-9933722.jpg",
      "url": "https://tw.buy.yahoo.com/gdsale/gdsale.asp?gdid=9933722",
      "platform": "yahoo_rushbuy"
    },
    {
      "title": "SOPHIA蘇菲亞珠寶 - 多款典雅鑽石項墜/耳環 任選",
      "price": 4500,
      "image_url": "https://img.yec.tw/zp/MerchandiseImages/930D856A54-SP-20928431.jpg",
      "url": "https://tw.buy.yahoo.com/gdsale/gdsale.asp?gdid=11763819",
      "platform": "yahoo_rushbuy"
    },
    {
      "title": "COACH 新色款 / 拉鏈中夾(多款均一價)",
      "price": 2450,
      "image_url": "https://img.yec.tw/zp/MerchandiseImages/0AB83FDCE4-Gd-11545403.jpg",
      "url": "https://tw.buy.yahoo.com/gdsale/gdsale.asp?gdid=11545403",
      "platform": "yahoo_rushbuy"
    },
    {
      "title": "【PowerA】|任天堂官方授權| 有線耳機(NSHS0299-01)-2款任選",
      "price": 1099,
      "image_url": "https://img.yec.tw/zp/MerchandiseImages/6AA3BE8FA7-Gd-11773329.jpg",
      "url": "https://tw.buy.yahoo.com/gdsale/gdsale.asp?gdid=11773329",
      "platform": "yahoo_rushbuy"
    },
    {
      "title": "TIGER虎牌 (買1送1) 超輕量手提隨行旋蓋不鏽鋼保溫杯480ml(MEA-B048+MEA-A048)",
      "price": 898,
      "image_url": "https://img.yec.tw/zp/MerchandiseImages/140612FB53-Product-33444037.jpg",
      "url": "https://tw.buy.yahoo.com/gdsale/gdsale.asp?gdid=10792154",
      "platform": "yahoo_rushbuy"
    },
    {
      "title": "DR.WU角鯊潤澤修復精華油30mL(共2入組)(買1送1)",
      "price": 2000,
      "image_url": "https://img.yec.tw/zp/MerchandiseImages/2FC6078722-Gd-11042107.jpg",
      "url": "https://tw.buy.yahoo.com/gdsale/gdsale.asp?gdid=11042107",
      "platform": "yahoo_rushbuy"
    },
    {
      "title": "2024 Apple Mac mini/M4晶片/10核心CPU 10核心GPU/16G/256GB SSD-MU9D3TA/A",
      "price": 18599,
      "image_url": "https://img.yec.tw/zp/MerchandiseImages/14D7B28F48-SP-18683936.jpg",
      "url": "https://tw.buy.yahoo.com/gdsale/gdsale.asp?gdid=11432300",
      "platform": "yahoo_rushbuy"
    },
    {
      "title": "【時時樂】ANDYMAY2 日出抽屜收納推車_雙層+三層 OH-R200【書包架 收納推車 收納車 收納架 附輪推車架】",
      "price": 549,
      "image_url": "https://img.yec.tw/zp/MerchandiseImages/6e48a03b27-Gd-11765540.jpg",
      "url": "https://tw.buy.yahoo.com/gdsale/gdsale.asp?gdid=11765540",
      "platform": "yahoo_rushbuy"
    },
    {
      "title": "糖村 法式金賞牛軋糖手提3盒組(原味/太妃/蔓越莓/中秋禮盒)",
      "price": 799,
      "image_url": "https://img.yec.tw/zp/MerchandiseImages/1DBC0576D6-Gd-11394988.jpg",
      "url": "https://tw.buy.yahoo.com/gdsale/gdsale.asp?gdid=11394988",
      "platform": "yahoo_rushbuy"
    },
    {
      "title": "HERAN 禾聯 14吋智能變頻DC風扇 HDF-14WT760 [限時優惠]",
      "price": 999,
      "image_url": "https://img.yec.tw/zp/MerchandiseImages/AB3948D99A-SP-19188974.jpg",
      "url": "https://tw.buy.yahoo.com/gdsale/gdsale.asp?gdid=11548961",
      "platform": "yahoo_rushbuy"
    },
    {
      "title": "羅技 logitech G G304無線電競滑鼠-黑",
      "price": 799,
      "image_url": "https://img.yec.tw/zp/MerchandiseImages/0B984CA535-Product-31150934.jpg",
      "url": "https://tw.buy.yahoo.com/gdsale/gdsale.asp?gdid=10303773",
      "platform": "yahoo_rushbuy"
    },
    {
      "title": "Fila Filament/Shuttle/Superstride/Molecules 男女 老爹鞋 慢跑鞋 運動 休閒 舒適 透氣 緩震 (多款任選)",
      "price": 899,
      "image_url": "https://img.yec.tw/zp/MerchandiseImages/76a01f766a-Gd-11707393.jpg",
      "url": "https://tw.buy.yahoo.com/gdsale/gdsale.asp?gdid=11707393",
      "platform": "yahoo_rushbuy"
    },
    {
      "title": "【SAMPO 聲寶】五段式音波震動牙刷共附9刷頭(三年份刷頭超值組)",
      "price": 699,
      "image_url": "https://img.yec.tw/zp/MerchandiseImages/db71282e65-Gd-9482328.jpg",
      "url": "https://tw.buy.yahoo.com/gdsale/gdsale.asp?gdid=9482328",
      "platform": "yahoo_rushbuy"
    },
    {
      "title": "【LISTERINE】薄荷漱口水 750mlx6入囤貨組(共4500ml)_德國境內版",
      "price": 699,
      "image_url": "https://img.yec.tw/zp/MerchandiseImages/a1ed7411b7-Gd-11767414.jpg",
      "url": "https://tw.buy.yahoo.com/gdsale/gdsale.asp?gdid=11767414",
      "platform": "yahoo_rushbuy"
    },
    {
      "title": "BraceUP 美國品牌 精選運動健身配件 多款任選",
      "price": 589,
      "image_url": "https://img.yec.tw/zp/MerchandiseImages/9870A1C5CC-SP-19936964.jpg",
      "url": "https://tw.buy.yahoo.com/gdsale/gdsale.asp?gdid=11604948",
      "platform": "yahoo_rushbuy"
    },
    {
      "title": "Kanebo 佳麗寶 ALLIE UV防曬水凝乳 90g ALLIE UV防曬水凝乳 90gx2+40g▼品牌慶爆款",
      "price": 1129,
      "image_url": "https://img.yec.tw/zp/MerchandiseImages/f73b0778ac-Gd-10999849.jpg",
      "url": "https://tw.buy.yahoo.com/gdsale/gdsale.asp?gdid=10999849",
      "platform": "yahoo_rushbuy"
    },
    {
      "title": "DON 3D釋壓記憶枕/乳膠頸椎牽引枕(買1送1)多色任選 快速出貨",
      "price": 799,
      "image_url": "https://img.yec.tw/zp/MerchandiseImages/2172f3a20e-Gd-10082382.jpg",
      "url": "https://tw.buy.yahoo.com/gdsale/gdsale.asp?gdid=10082382",
      "platform": "yahoo_rushbuy"
    },
    {
      "title": "【限量絕版品包款】NINE WEST 品牌經典手提托特包/斜背/水桶/兩用包",
      "price": 999,
      "image_url": "https://img.yec.tw/zp/MerchandiseImages/6f92a6dcba-Gd-11634349.jpg",
      "url": "https://tw.buy.yahoo.com/gdsale/gdsale.asp?gdid=11634349",
      "platform": "yahoo_rushbuy"
    },
    {
      "title": "白蘭 4X極淨酵素抗病毒洗衣球補充包(30顆/袋)_4入組(三款任選)",
      "price": 499,
      "image_url": "https://img.yec.tw/zp/MerchandiseImages/D2855AD862-Gd-11206712.jpg",
      "url": "https://tw.buy.yahoo.com/gdsale/gdsale.asp?gdid=11206712",
      "platform": "yahoo_rushbuy"
    },
    {
      "title": "JSmax SW-BK01健康管理AI智慧通話手錶",
      "price": 2999,
      "image_url": "https://img.yec.tw/zp/MerchandiseImages/61A9D44971-SP-16915521.jpg",
      "url": "https://tw.buy.yahoo.com/gdsale/gdsale.asp?gdid=11074292",
      "platform": "yahoo_rushbuy"
    },
    {
      "title": "(領券再折)阿仁304不鏽鋼曬衣架 吊衣架 晾衣架 掛衣架 台灣製造 長方形28夾",
      "price": 690,
      "image_url": "https://img.yec.tw/cl/api/res/1.2/ccCMwmVSa8heCswMT30_rQ--/YXBwaWQ9eXR3bWFsbDtoPTYwMDtxPTEwMDt3PTYwMA--/https://img.yec.tw/fy/e153/item/p0294186438619-item-bfc2xf4x1000x1000-m.jpg",
      "url": "https://tw.buy.yahoo.com/gdsale/gdsale.asp?gdid=p0294186438619",
      "platform": "yahoo_rushbuy"
    },
    {
      "title": "【品樂生活】MIT雙桿伸縮鞋網曬衣架(附輪組) HA-042BK 雙桿衣架 曬鞋架 衣架 伸縮衣架",
      "price": 399,
      "image_url": "https://img.yec.tw/cl/api/res/1.2/wXj_EBaHW3ijVBAavfdRVA--/YXBwaWQ9eXR3bWFsbDtoPTYwMDtxPTEwMDt3PTYwMA--/https://img.yec.tw/fy/a378/item/p0261264677882-item-d24dxf4x1000x1000-m.jpg",
      "url": "https://tw.buy.yahoo.com/gdsale/gdsale.asp?gdid=p0261264677882",
      "platform": "yahoo_rushbuy"
    },
    {
      "title": "finish亮碟-洗碗機強力洗滌粉劑洗碗粉1kgx2(入門必備/雙倍酵素/強效去油去漬/全機型適用)",
      "price": 619,
      "image_url": "https://img.yec.tw/zp/MerchandiseImages/59a2b776dd-Gd-7201646.jpg",
      "url": "https://tw.buy.yahoo.com/gdsale/gdsale.asp?gdid=7201646",
      "platform": "yahoo_rushbuy"
    }
  ],
  "crawl_time": "2025-09-12 12:24:32"
}