{
  "platform": "yahoo_rushbuy",
  "keyword": "yahoo_rushbuy",
  "total_products": 27,
  "products": [
    {
      "title": "INNISFREE 無油無慮礦物控油蜜粉 5g (乾洗髮控油神器) 2入組",
      "price": 250,
      "image_url": "https://img.yec.tw/zp/MerchandiseImages/05a5e7f2db-Gd-11040759.jpg",
      "url": "https://tw.buy.yahoo.com/gdsale/gdsale.asp?gdid=11040759",
      "platform": "yahoo_rushbuy"
    },
    {
      "title": "DR.WU角鯊潤澤修復精華油30mL(共2入組)(買1送1)",
      "price": 2000,
      "image_url": "https://img.yec.tw/zp/MerchandiseImages/1405590486-Gd-11042107.jpg",
      "url": "https://tw.buy.yahoo.com/gdsale/gdsale.asp?gdid=11042107",
      "platform": "yahoo_rushbuy"
    },
    {
      "title": "鼎泰豐 金磚旺來鳳梨酥禮盒10入(380g/盒) 1+1組合(共2盒)",
      "price": 799,
      "image_url": "https://img.yec.tw/zp/MerchandiseImages/8F64D8F773-Gd-11780209.jpg",
      "url": "https://tw.buy.yahoo.com/gdsale/gdsale.asp?gdid=11780209",
      "platform": "yahoo_rushbuy"
    },
    {
      "title": "精英 LIVA Z3 四核心迷你電腦 (N6000/4G/128G/Win11P)",
      "price": 7690,
      "image_url": "https://img.yec.tw/zp/MerchandiseImages/6EC3F861CE-SP-13634939.jpg",
      "url": "https://tw.buy.yahoo.com/gdsale/gdsale.asp?gdid=10528930",
      "platform": "yahoo_rushbuy"
    },
    {
      "title": "PALLADIUM PAMPA RCYCL LITE+WP+ ZIP再生科技輕量拉鍊橘標防水靴-中性 多款任選",
      "price": 3050,
      "image_url": "https://img.yec.tw/zp/MerchandiseImages/5659B46CE6-SP-19607936.jpg",
      "url": "https://tw.buy.yahoo.com/gdsale/gdsale.asp?gdid=11569990",
      "platform": "yahoo_rushbuy"
    },
    {
      "title": "PNY GeForce RTX5080 ARGB EPIC-X RGB超頻三風扇 GPU VCG508016TFXXPB1-O顯示卡",
      "price": 36990,
      "image_url": "https://img.yec.tw/zp/MerchandiseImages/040F579419-SP-20632870.jpg",
      "url": "https://tw.buy.yahoo.com/gdsale/gdsale.asp?gdid=11708290",
      "platform": "yahoo_rushbuy"
    },
    {
      "title": "Sharp 夏普 14吋 6段速微電腦遙控擺頭ECO溫控DC直流電風扇 PJ-E14GE 白色",
      "price": 1299,
      "image_url": "https://img.yec.tw/zp/MerchandiseImages/f2c6198f24-Gd-11693951.jpg",
      "url": "https://tw.buy.yahoo.com/gdsale/gdsale.asp?gdid=11693951",
      "platform": "yahoo_rushbuy"
    },
    {
      "title": "CHANEL香奈兒 COCO持色潤唇膏 3g 多款任選",
      "price": 1299,
      "image_url": "https://img.yec.tw/zp/MerchandiseImages/333B1DD3E3-Gd-11453312.jpg",
      "url": "https://tw.buy.yahoo.com/gdsale/gdsale.asp?gdid=11453312",
      "platform": "yahoo_rushbuy"
    },
    {
      "title": "DON 買一送一 100%純棉床包枕套三件組-多款任選(雙人/加大)",
      "price": 799,
      "image_url": "https://img.yec.tw/zp/MerchandiseImages/81229dbec9-Gd-10423956.jpg",
      "url": "https://tw.buy.yahoo.com/gdsale/gdsale.asp?gdid=10423956",
      "platform": "yahoo_rushbuy"
    },
    {
      "title": "Samsung Galaxy A56 (12G/256G) 6.7吋 3+1鏡頭智慧手機",
      "price": 11990,
      "image_url": "https://img.yec.tw/zp/MerchandiseImages/0B427A5DDD-SP-20007213.jpg",
      "url": "https://tw.buy.yahoo.com/gdsale/gdsale.asp?gdid=11626211",
      "platform": "yahoo_rushbuy"
    },
    {
      "title": "ALUXE 亞立詩 0.60克拉 FVS2 18K金 鑽石耳環(三款任選)",
      "price": 39999,
      "image_url": "https://img.yec.tw/zp/MerchandiseImages/11bac7a4c6-Gd-11774874.jpg",
      "url": "https://tw.buy.yahoo.com/gdsale/gdsale.asp?gdid=11774874",
      "platform": "yahoo_rushbuy"
    },
    {
      "title": "INNISFREE 1%A醇PDRN水光安瓶25ml(緊緻毛孔、水光精華)",
      "price": 980,
      "image_url": "https://img.yec.tw/zp/MerchandiseImages/04ffdf7668-Gd-11426540.jpg",
      "url": "https://tw.buy.yahoo.com/gdsale/gdsale.asp?gdid=11426540",
      "platform": "yahoo_rushbuy"
    },
    {
      "title": "【ONE HOUSE】爆品收納 均一價699",
      "price": 699,
      "image_url": "https://img.yec.tw/zp/MerchandiseImages/fa25931ea5-Gd-11771170.jpg",
      "url": "https://tw.buy.yahoo.com/gdsale/gdsale.asp?gdid=11771170",
      "platform": "yahoo_rushbuy"
    },
    {
      "title": "GOYARD 高雅德 Plumet Pocket 翻蓋釦式三層扁斜背包",
      "price": 45999,
      "image_url": "https://img.yec.tw/zp/MerchandiseImages/BFB6952408-Gd-11484359.jpg",
      "url": "https://tw.buy.yahoo.com/gdsale/gdsale.asp?gdid=11484359",
      "platform": "yahoo_rushbuy"
    },
    {
      "title": "寶島春風抽取式衛生紙130抽x8包x8串/箱",
      "price": 679,
      "image_url": "https://img.yec.tw/zp/MerchandiseImages/99086CF1D3-Gd-7746830.jpg",
      "url": "https://tw.buy.yahoo.com/gdsale/gdsale.asp?gdid=7746830",
      "platform": "yahoo_rushbuy"
    },
    {
      "title": "象印*0.72L*不銹鋼一體式杯蓋旋蓋式真空保溫保冷杯(SM-GA72)(快)",
      "price": 839,
      "image_url": "https://img.yec.tw/zp/MerchandiseImages/08d2fce480-Gd-10278427.jpg",
      "url": "https://tw.buy.yahoo.com/gdsale/gdsale.asp?gdid=10278427",
      "platform": "yahoo_rushbuy"
    },
    {
      "title": "[領券再92折] KIPLING最後限量★肩背/斜背/後背包組(多款任選)",
      "price": 1288,
      "image_url": "https://img.yec.tw/zp/MerchandiseImages/d45554263a-Gd-11742639.jpg",
      "url": "https://tw.buy.yahoo.com/gdsale/gdsale.asp?gdid=11742639",
      "platform": "yahoo_rushbuy"
    },
    {
      "title": "Seagate Expansion Desktop Drive 24TB 外接硬碟(STKP24000400)",
      "price": 14990,
      "image_url": "https://img.yec.tw/zp/MerchandiseImages/3945A4FC77-SP-20243396.jpg",
      "url": "https://tw.buy.yahoo.com/gdsale/gdsale.asp?gdid=11645394",
      "platform": "yahoo_rushbuy"
    },
    {
      "title": "【葡萄王】認證靈芝60粒x3瓶 (國家認證 有效調節免疫 )",
      "price": 999,
      "image_url": "https://img.yec.tw/zp/MerchandiseImages/3355e27094-Gd-8835245.jpg",
      "url": "https://tw.buy.yahoo.com/gdsale/gdsale.asp?gdid=8835245",
      "platform": "yahoo_rushbuy"
    },
    {
      "title": "SAMSUNG三星 237公升 1級變頻雙門電冰箱 RT22M4015S8/TW",
      "price": 11900,
      "image_url": "https://img.yec.tw/zp/MerchandiseImages/1EC066F516-SP-20248818.jpg",
      "url": "https://tw.buy.yahoo.com/gdsale/gdsale.asp?gdid=11647216",
      "platform": "yahoo_rushbuy"
    },
    {
      "title": "Apple iPhone 17 Pro Max 256G (銀/宇宙橙/藏藍)【預購-依訂單順序出貨】【愛買】",
      "price": 44900,
      "image_url": "https://img.yec.tw/cl/api/res/1.2/FpQwpFGIqYqLUf66mRqV7Q--/YXBwaWQ9eXR3bWFsbDtoPTYwMDtxPTEwMDt3PTYwMA--/https://img.yec.tw/fy/ad93/item/p0830265173060-item-e179xf4x0500x0500-m.jpg",
      "url": "https://tw.buy.yahoo.com/gdsale/gdsale.asp?gdid=p0830265173060",
      "platform": "yahoo_rushbuy"
    },
    {
      "title": "【喜憨兒~送愛到部落】2025中秋禮盒募集 (您不會收到商品)(公益)",
      "price": 499,
      "image_url": "https://img.yec.tw/cl/api/res/1.2/BVPCbDmceFHrsEYFInIrmQ--/YXBwaWQ9eXR3bWFsbDtoPTYwMDtxPTEwMDt3PTYwMA--/https://img.yec.tw/fy/8b39/item/p0084265044750-item-1427xf4x1000x1000-m.jpg",
      "url": "https://tw.buy.yahoo.com/gdsale/gdsale.asp?gdid=p0084265044750",
      "platform": "yahoo_rushbuy"
    },
    {
      "title": "SINDIP 前開行李箱 20吋 海關鎖+靜音輪+可擴展",
      "price": 1379,
      "image_url": "https://img.yec.tw/cl/api/res/1.2/BG1dqnfXtQNwXe5Xtr7c8g--/YXBwaWQ9eXR3bWFsbDtoPTYwMDtxPTEwMDt3PTYwMA--/https://img.yec.tw/fy/ac9b/item/p0827264245895-item-707exf4x1400x1400-m.jpg",
      "url": "https://tw.buy.yahoo.com/gdsale/gdsale.asp?gdid=p0827264245895",
      "platform": "yahoo_rushbuy"
    },
    {
      "title": "【義美生醫】漩過溪瑪卡膠囊(120粒/盒)",
      "price": 768,
      "image_url": "https://img.yec.tw/zp/MerchandiseImages/C753F99C36-SP-11132801.jpg",
      "url": "https://tw.buy.yahoo.com/gdsale/gdsale.asp?gdid=9935278",
      "platform": "yahoo_rushbuy"
    },
    {
      "title": "(領券折後$999) MIZUNO美津濃 SPARK 9 男女慢跑鞋 任選",
      "price": 999,
      "image_url": "https://img.yec.tw/zp/MerchandiseImages/b9a0aef38f-Gd-11664852.jpg",
      "url": "https://tw.buy.yahoo.com/gdsale/gdsale.asp?gdid=11664852",
      "platform": "yahoo_rushbuy"
    },
    {
      "title": "3M 德國進口表布100%防蹣枕心-舒適型加厚版(2入組)",
      "price": 999,
      "image_url": "https://img.yec.tw/zp/MerchandiseImages/fc20719164-Gd-6114015.jpg",
      "url": "https://tw.buy.yahoo.com/gdsale/gdsale.asp?gdid=6114015",
      "platform": "yahoo_rushbuy"
    },
    {
      "title": "【AHC】大馬士革玫瑰全臉六角修護緊緻眼霜40ml _3入組",
      "price": 1099,
      "image_url": "https://img.yec.tw/zp/MerchandiseImages/4958b119a0-Gd-11610396.jpg",
      "url": "https://tw.buy.yahoo.com/gdsale/gdsale.asp?gdid=11610396",
      "platform": "yahoo_rushbuy"
    }
  ],
  "crawl_time": "2025-09-22 18:20:19"
}