{
  "platform": "yahoo_rushbuy",
  "keyword": "yahoo_rushbuy",
  "total_products": 27,
  "products": [
    {
      "title": "【Deseno 笛森諾】尊爵傳奇V 25吋 前開式可擴充拉鍊行李箱(多色任選)時時樂限定",
      "price": 4590,
      "image_url": "https://img.yec.tw/zp/MerchandiseImages/3B02837F2C-SP-21084481.jpg",
      "url": "https://tw.buy.yahoo.com/gdsale/gdsale.asp?gdid=11797777",
      "platform": "yahoo_rushbuy"
    },
    {
      "title": "【BHK’s】100%膠原蛋白粉 (3g/條；30條/盒)3盒組",
      "price": 1430,
      "image_url": "https://img.yec.tw/zp/MerchandiseImages/AB0216F7C4-SP-12331816.jpg",
      "url": "https://tw.buy.yahoo.com/gdsale/gdsale.asp?gdid=10266986",
      "platform": "yahoo_rushbuy"
    },
    {
      "title": "【Bone 蹦克】斜背頸掛手機綁四代 手機掛繩 手機配件 手機周邊 手機吊繩 手機繩斜背",
      "price": 499,
      "image_url": "https://img.yec.tw/zp/MerchandiseImages/E11B4358C3-SP-18790417.jpg",
      "url": "https://tw.buy.yahoo.com/gdsale/gdsale.asp?gdid=11457483",
      "platform": "yahoo_rushbuy"
    },
    {
      "title": "幸福移動餐車營業中！本日限定漬佐紫蘇飯糰，請慢用【城邦讀書花園】",
      "price": 250,
      "image_url": "https://img.yec.tw/zp/MerchandiseImages/351D2175F2-SP-18521077.jpg",
      "url": "https://tw.buy.yahoo.com/gdsale/gdsale.asp?gdid=11398270",
      "platform": "yahoo_rushbuy"
    },
    {
      "title": "LOEWE 羅威 羊毛馬海毛混紡壓花皮標流蘇圍巾-多款可選",
      "price": 9500,
      "image_url": "https://img.yec.tw/zp/MerchandiseImages/3E52AEE322-Gd-11789420.jpg",
      "url": "https://tw.buy.yahoo.com/gdsale/gdsale.asp?gdid=11789420",
      "platform": "yahoo_rushbuy"
    },
    {
      "title": "【Mio】MiVue C590 安全預警六合一 星光級 GPS行車記錄器(送-32G卡)-快",
      "price": 2540,
      "image_url": "https://img.yec.tw/zp/MerchandiseImages/A8690E6563-SP-19326011.jpg",
      "url": "https://tw.buy.yahoo.com/gdsale/gdsale.asp?gdid=11525366",
      "platform": "yahoo_rushbuy"
    },
    {
      "title": "BOSCH博世 10公斤去漬抗敏洗衣機+9公斤熱泵乾衣機 (WGA15200TC+WQB245B0TC)",
      "price": 88888,
      "image_url": "https://img.yec.tw/zp/MerchandiseImages/6D1F9A14C8-SP-20893617.jpg",
      "url": "https://tw.buy.yahoo.com/gdsale/gdsale.asp?gdid=11757119",
      "platform": "yahoo_rushbuy"
    },
    {
      "title": "【Durex杜蕾斯】 超薄裝保險套12入x4盒（共48入）",
      "price": 899,
      "image_url": "https://img.yec.tw/zp/MerchandiseImages/8B63C73A4F-Gd-10690724.jpg",
      "url": "https://tw.buy.yahoo.com/gdsale/gdsale.asp?gdid=10690724",
      "platform": "yahoo_rushbuy"
    },
    {
      "title": "ASUS X1504VA 15.6吋特仕筆電 (i5-1334U/8G+8G/1TB SSD/午夜藍/Vivobook 15)",
      "price": 19499,
      "image_url": "https://img.yec.tw/zp/MerchandiseImages/011BC51319-SP-20046478.jpg",
      "url": "https://tw.buy.yahoo.com/gdsale/gdsale.asp?gdid=11617388",
      "platform": "yahoo_rushbuy"
    },
    {
      "title": "【Nintendo 任天堂】Switch 2 NS2 瑪利歐賽車世界 主機組合 台灣公司貨",
      "price": 14980,
      "image_url": "https://img.yec.tw/zp/MerchandiseImages/775FF18047-Gd-11679164.jpg",
      "url": "https://tw.buy.yahoo.com/gdsale/gdsale.asp?gdid=11679164",
      "platform": "yahoo_rushbuy"
    },
    {
      "title": "K-SWISS Court Tiebreak II Court Base II 時尚運動鞋 小白鞋 男女 多款任選",
      "price": 1190,
      "image_url": "https://img.yec.tw/zp/MerchandiseImages/e873165eeb-Gd-11673935.jpg",
      "url": "https://tw.buy.yahoo.com/gdsale/gdsale.asp?gdid=11673935",
      "platform": "yahoo_rushbuy"
    },
    {
      "title": "五月花新柔韌抽取衛生紙110抽 x72包/箱",
      "price": 799,
      "image_url": "https://img.yec.tw/zp/MerchandiseImages/59779EBA38-Gd-5281152.jpg",
      "url": "https://tw.buy.yahoo.com/gdsale/gdsale.asp?gdid=5281152",
      "platform": "yahoo_rushbuy"
    },
    {
      "title": "趨勢PC-cillin 2025 防毒版 三年一台標準盒裝",
      "price": 499,
      "image_url": "https://img.yec.tw/zp/MerchandiseImages/4b29412c7e-Gd-11302458.jpg",
      "url": "https://tw.buy.yahoo.com/gdsale/gdsale.asp?gdid=11302458",
      "platform": "yahoo_rushbuy"
    },
    {
      "title": "唯衣 6款選/5件組 提拉塑形聚攏防垂粉底液美背內衣-無鋼圈無痕調整型內衣_顏色隨機_82602(M-3XL可選)",
      "price": 698,
      "image_url": "https://img.yec.tw/zp/MerchandiseImages/D15F30050E-SP-20974367.jpg",
      "url": "https://tw.buy.yahoo.com/gdsale/gdsale.asp?gdid=11772144",
      "platform": "yahoo_rushbuy"
    },
    {
      "title": "【CITIZEN 星辰】星辰金銀雙色防水錶(BI5056-58A)",
      "price": 3980,
      "image_url": "https://img.yec.tw/zp/MerchandiseImages/E75FDF50FF-SP-9232898.jpg",
      "url": "https://tw.buy.yahoo.com/gdsale/gdsale.asp?gdid=9290830",
      "platform": "yahoo_rushbuy"
    },
    {
      "title": "Baan 貝恩 嬰兒泡泡香浴組(泡泡香浴露500ml+800ml補充包)",
      "price": 669,
      "image_url": "https://img.yec.tw/zp/MerchandiseImages/0560fccc9d-Gd-11100217.jpg",
      "url": "https://tw.buy.yahoo.com/gdsale/gdsale.asp?gdid=11100217",
      "platform": "yahoo_rushbuy"
    },
    {
      "title": "SHISEIDO資生堂 怡麗絲爾 膠原彈潤多效美肌乳 SPF50+ PA++++35ml 全新小金管 專櫃公司貨",
      "price": 599,
      "image_url": "https://img.yec.tw/zp/MerchandiseImages/938202C0D7-SP-19485542.jpg",
      "url": "https://tw.buy.yahoo.com/gdsale/gdsale.asp?gdid=11549189",
      "platform": "yahoo_rushbuy"
    },
    {
      "title": "【New Balance】緞帶款327系列+海鹽藍574(厚底)_女款任選",
      "price": 1599,
      "image_url": "https://img.yec.tw/zp/MerchandiseImages/d50f4d6efb-Gd-11459966.jpg",
      "url": "https://tw.buy.yahoo.com/gdsale/gdsale.asp?gdid=11459966",
      "platform": "yahoo_rushbuy"
    },
    {
      "title": "義大利賈柯巴齊0酒精香檳飲 (750ml)_1+1組合(共2瓶)",
      "price": 688,
      "image_url": "https://img.yec.tw/zp/MerchandiseImages/C016B80C7F-Gd-11795656.jpg",
      "url": "https://tw.buy.yahoo.com/gdsale/gdsale.asp?gdid=11795656",
      "platform": "yahoo_rushbuy"
    },
    {
      "title": "vivo X200 FE 5G (12G/512G) 6.31吋八核心智慧型手機",
      "price": 16990,
      "image_url": "https://img.yec.tw/zp/MerchandiseImages/2AE46E7114-SP-20936901.jpg",
      "url": "https://tw.buy.yahoo.com/gdsale/gdsale.asp?gdid=11766727",
      "platform": "yahoo_rushbuy"
    },
    {
      "title": "斜背包 日系簡約雙層A4側背包包 大容量 防水 男 女 男包 現貨 NEW STAR BL161",
      "price": 990,
      "image_url": "https://img.yec.tw/cl/api/res/1.2/KmhIIqMaOKbYQV4FLVoFfQ--/YXBwaWQ9eXR3bWFsbDtoPTYwMDtxPTEwMDt3PTYwMA--/https://img.yec.tw/fy/962d/item/p0202193813951-item-1d3bxf4x1000x1000-m.jpg",
      "url": "https://tw.buy.yahoo.com/gdsale/gdsale.asp?gdid=p0202193813951",
      "platform": "yahoo_rushbuy"
    },
    {
      "title": "[時時樂限定$1198 9/29 10:00-10/1 10:00] 威瑪索 氣壓升降床邊桌/桌面可折疊懶人桌-(4色)",
      "price": 1198,
      "image_url": "https://img.yec.tw/cl/api/res/1.2/.v4hMSgvD2rjdpf26vZ2rg--/YXBwaWQ9eXR3bWFsbDtoPTYwMDtxPTEwMDt3PTYwMA--/https://img.yec.tw/fy/a349/item/p0065264973798-item-a808xf4x1000x1000-m.jpg",
      "url": "https://tw.buy.yahoo.com/gdsale/gdsale.asp?gdid=p0065264973798",
      "platform": "yahoo_rushbuy"
    },
    {
      "title": "【LARGAN 大立美】晶亮立克5盒(30粒/盒)_大立光集團所屬_美鳳有約冠名推薦",
      "price": 3299,
      "image_url": "https://img.yec.tw/zp/MerchandiseImages/75f1600f6c-Gd-11307022.jpg",
      "url": "https://tw.buy.yahoo.com/gdsale/gdsale.asp?gdid=11307022",
      "platform": "yahoo_rushbuy"
    },
    {
      "title": "御慈燕窩 極品即食燕窩禮盒5瓶裝/盒(買一盒送一盒)(BO0126)",
      "price": 1880,
      "image_url": "https://img.yec.tw/cl/api/res/1.2/wGx_Hf2Ti81Ww6mFFxY8Sg--/YXBwaWQ9eXR3bWFsbDtoPTYwMDtxPTEwMDt3PTYwMA--/https://img.yec.tw/fy/e60f/item/p0762261161177-item-ec45xf4x1000x1000-m.jpg",
      "url": "https://tw.buy.yahoo.com/gdsale/gdsale.asp?gdid=p0762261161177",
      "platform": "yahoo_rushbuy"
    },
    {
      "title": "【喜憨兒 送愛到偏鄉】愛心餐盒認購◆方案一◆每月配送一次×配送一學期(公益)",
      "price": 600,
      "image_url": "https://img.yec.tw/cl/api/res/1.2/3TIcMH5Vvyf_mNQZlAZ5Eg--/YXBwaWQ9eXR3bWFsbDtoPTYwMDtxPTEwMDt3PTYwMA--/https://img.yec.tw/fy/e217/item/p0084178927620-item-394exf4x1001x1001-m.jpg",
      "url": "https://tw.buy.yahoo.com/gdsale/gdsale.asp?gdid=p0084178927620",
      "platform": "yahoo_rushbuy"
    },
    {
      "title": "SHISEIDO資生堂 安耐曬 金鑽高效防曬露NA 5X版 60ml 2入 專櫃公司貨",
      "price": 888,
      "image_url": "https://img.yec.tw/zp/MerchandiseImages/7B3A74A4B6-Gd-11747132.jpg",
      "url": "https://tw.buy.yahoo.com/gdsale/gdsale.asp?gdid=11747132",
      "platform": "yahoo_rushbuy"
    },
    {
      "title": "【悠活原力】原力維生素D 800IU錠(120錠/瓶) x5瓶",
      "price": 1099,
      "image_url": "https://img.yec.tw/zp/MerchandiseImages/1333ECA91D-SP-19136954.jpg",
      "url": "https://tw.buy.yahoo.com/gdsale/gdsale.asp?gdid=11503267",
      "platform": "yahoo_rushbuy"
    }
  ],
  "crawl_time": "2025-09-29 12:26:34"
}